pydatk/__init__.py
pydatk/finance.py
pydatk-0.0.1.dist-info/licenses/LICENSE
pydatk-0.0.1.dist-info/METADATA
pydatk-0.0.1.dist-info/WHEEL
pydatk-0.0.1.dist-info/top_level.txt
pydatk-0.0.1.dist-info/RECORD
