Metadata-Version: 2.4
Name: pydatk
Version: 0.0.1
Summary: pydatk
Author-email: pydatk <dev@pydatk.com>
License-Expression: GPL-3.0-or-later
Project-URL: Homepage, https://www.pydatk.com
Project-URL: Documentation, https://www.pydatk.com
Project-URL: Repository, https://github.com/pydatk/pydatk
Project-URL: Discussion, https://github.com/pydatk/pydatk/discussions
Project-URL: Issues, https://github.com/pydatk/pydatk/issues
Project-URL: Changelog, https://github.com/pydatk/pydatk/blob/main/CHANGELOG.md
Classifier: Programming Language :: Python :: 3
Classifier: Operating System :: OS Independent
Requires-Python: >=3.13
License-File: LICENSE
Dynamic: license-file
